testpackage/__init__.py
caixaequ2ahzoop-2.0.1.dist-info/METADATA
caixaequ2ahzoop-2.0.1.dist-info/WHEEL
caixaequ2ahzoop-2.0.1.dist-info/top_level.txt
caixaequ2ahzoop-2.0.1.dist-info/RECORD
