Metadata-Version: 2.1
Name: caiXaequ2Ahzoop
Version: 2.0.1
Summary: caiXaequ2Ahzoop
Author-email: caiXaequ2Ahzoop <caiXaequ2Ahzoop@caiXaequ2Ahzoop.com>
License: MIT
Classifier: Programming Language :: Python :: 3
Classifier: License :: OSI Approved :: MIT License
Classifier: Operating System :: OS Independent
Requires-Python: >=3.7
